svlearn/utils.py
svlearn-0.0.3.dev8.dist-info/LICENSE
svlearn-0.0.3.dev8.dist-info/METADATA
svlearn-0.0.3.dev8.dist-info/WHEEL
svlearn-0.0.3.dev8.dist-info/top_level.txt
svlearn-0.0.3.dev8.dist-info/RECORD
