Metadata-Version: 2.1
Name: svlearn
Version: 0.0.3.dev8
Summary: Utils for ML
Home-page: UNKNOWN
Author: bvoleti-p
Author-email: 
License: UNKNOWN
Platform: UNKNOWN
Classifier: Programming Language :: Python :: 3
Classifier: License :: OSI Approved :: BSD License
Classifier: Operating System :: OS Independent
Requires-Python: >=3.6
Requires-Dist: markdown
Requires-Dist: numpy
Requires-Dist: pandas
Requires-Dist: sklearn
Requires-Dist: scipy
Requires-Dist: matplotlib
Requires-Dist: seaborn
Requires-Dist: statsmodels
Requires-Dist: keras
Requires-Dist: IPython
Requires-Dist: missingno
Requires-Dist: category-encoders
Requires-Dist: tensorflow
